Digital_Forming_Solution/Select_Operations.py
Digital_Forming_Solution/__init__.py
Digital_Forming_Solution-0.1.13.dist-info/METADATA
Digital_Forming_Solution-0.1.13.dist-info/WHEEL
Digital_Forming_Solution-0.1.13.dist-info/top_level.txt
Digital_Forming_Solution-0.1.13.dist-info/RECORD
