Metadata-Version: 2.1
Name: Digital-Forming-Solution
Version: 0.1.13
Summary: DFS Projects Some of the Packages it help to perform task easily
Author: Bharatesha N S
Author-email: bharatesha.ns.ext@bayer.com
Classifier: Programming Language :: Python :: 3
Classifier: License :: OSI Approved :: MIT License
Classifier: Operating System :: OS Independent
Requires-Python: >=3.6
